{
  "trackers": [
    {
      "type": "unknown",
      "url": "https://static.cloudflareinsights.com/beacon.min.js/v8b253dfea2ab4077af8c6f58422dfbfd1689876627854"
    },
    {
      "type": "unknown",
      "url": "https://client.crisp.chat/l.js"
    },
    {
      "type": "unknown",
      "url": "https://static.userguiding.com/media/user-guiding-006614964ID-embedded.js"
    },
    {
      "type": "unknown",
      "url": "https://client.crisp.chat/static/javascripts/client.js?cf67b1b"
    },
    {
      "type": "unknown",
      "url": "https://client.crisp.chat/static/stylesheets/client_default.css?cf67b1b"
    },
    {
      "type": "unknown",
      "url": "https://rlarzronkgoyvtdkltqy.supabase.co/rest/v1/ongoing_maintenance?select=*"
    },
    {
      "type": "unknown",
      "url": "https://client.crisp.chat/settings/website/582ff50a-5ac4-4f38-a8bc-62f51beeef89/prelude/?callback=window.%24__CRISP_INSTANCE.__spool.website_handler&2023-7-13-19-58"
    },
    {
      "type": "unknown",
      "url": "https://rlarzronkgoyvtdkltqy.supabase.co/rest/v1/ongoing_maintenance?select=*"
    },
    {
      "type": "unknown",
      "url": "https://static.userguiding.com/media/sdk-006614964ID.json"
    },
    {
      "type": "unknown",
      "url": "https://metrics.userguiding.com/sdk/ping/66149"
    },
    {
      "type": "unknown",
      "url": "https://client.crisp.chat/settings/website/582ff50a-5ac4-4f38-a8bc-62f51beeef89/?callback=window.%24__CRISP_INSTANCE.__spool.website_handler&1691158876707"
    },
    {
      "type": "unknown",
      "url": "https://client.crisp.chat/static/javascripts/locales/fr.js?cf67b1b"
    },
    {
      "type": "unknown",
      "url": "https://image.crisp.chat/process/thumbnail/?url=https%3A%2F%2Fstorage.crisp.chat%2Fusers%2Favatar%2Foperator%2F697bdaa6c64aec00%2Fmememepng_1ghcm7x.png&width=240&height=240&1691158876707"
    }
  ],
  "cookies": [],
  "headers": {
    "alt-svc": "h3=\":443\"; ma=86400",
    "cache-control": "public, max-age=0",
    "cf-cache-status": "DYNAMIC",
    "cf-ray": "7f6388169e6b485b-DFW",
    "content-encoding": "br",
    "content-type": "text/html; charset=UTF-8",
    "date": "Sun, 13 Aug 2023 19:58:13 GMT",
    "last-modified": "Thu, 03 Aug 2023 14:12:18 GMT",
    "nel": "{\"success_fraction\":0,\"report_to\":\"cf-nel\",\"max_age\":604800}",
    "report-to": "{\"endpoints\":[{\"url\":\"https:\\/\\/a.nel.cloudflare.com\\/report\\/v3?s=L0oOJZQvjLDTTzU%2BVDJVammkdIcRZibLYoRobpVs2qmwXpNSffEVD8KK1mhKsLyXUS1xK%2BtCQFnfErRv0u6s48FcdCtDhdn6QzXwWmmreAFqehb42ziwpGyhhrdnoYy3dffvlskLUtrgeIMibLxSn4lK\"}],\"group\":\"cf-nel\",\"max_age\":604800}",
    "server": "cloudflare",
    "x-powered-by": "Express",
    "x-request-id": "e663ba82-9033-4979-9a95-6c4a0e9d9475"
  },
  "endpoints": [
    {
      "hostname": "app.territoiresentransitions.fr",
      "ip": "172.67.195.83",
      "geoip": {
        "continent": {
          "code": "NA",
          "geoname_id": 6255149,
          "names": {
            "de": "Nordamerika",
            "en": "North America",
            "es": "Norteamérica",
            "fr": "Amérique du Nord",
            "ja": "北アメリカ",
            "pt-BR": "América do Norte",
            "ru": "Северная Америка",
            "zh-CN": "北美洲"
          }
        },
        "country": {
          "geoname_id": 6252001,
          "iso_code": "US",
          "names": {
            "de": "Vereinigte Staaten",
            "en": "United States",
            "es": "Estados Unidos",
            "fr": "États Unis",
            "ja": "アメリカ",
            "pt-BR": "EUA",
            "ru": "США",
            "zh-CN": "美国"
          }
        },
        "location": {
          "accuracy_radius": 1000,
          "latitude": 37.751,
          "longitude": -97.822,
          "time_zone": "America/Chicago"
        },
        "registered_country": {
          "geoname_id": 6252001,
          "iso_code": "US",
          "names": {
            "de": "Vereinigte Staaten",
            "en": "United States",
            "es": "Estados Unidos",
            "fr": "États Unis",
            "ja": "アメリカ",
            "pt-BR": "EUA",
            "ru": "США",
            "zh-CN": "美国"
          }
        }
      }
    },
    {
      "hostname": "static.cloudflareinsights.com",
      "ip": "104.16.57.101",
      "geoip": {
        "registered_country": {
          "geoname_id": 6252001,
          "iso_code": "US",
          "names": {
            "de": "Vereinigte Staaten",
            "en": "United States",
            "es": "Estados Unidos",
            "fr": "États Unis",
            "ja": "アメリカ",
            "pt-BR": "EUA",
            "ru": "США",
            "zh-CN": "美国"
          }
        }
      }
    },
    {
      "hostname": "client.crisp.chat",
      "ip": "104.18.28.91",
      "geoip": {
        "registered_country": {
          "geoname_id": 6252001,
          "iso_code": "US",
          "names": {
            "de": "Vereinigte Staaten",
            "en": "United States",
            "es": "Estados Unidos",
            "fr": "États Unis",
            "ja": "アメリカ",
            "pt-BR": "EUA",
            "ru": "США",
            "zh-CN": "美国"
          }
        }
      }
    },
    {
      "hostname": "static.userguiding.com",
      "ip": "104.26.4.5",
      "geoip": {
        "registered_country": {
          "geoname_id": 6252001,
          "iso_code": "US",
          "names": {
            "de": "Vereinigte Staaten",
            "en": "United States",
            "es": "Estados Unidos",
            "fr": "États Unis",
            "ja": "アメリカ",
            "pt-BR": "EUA",
            "ru": "США",
            "zh-CN": "美国"
          }
        }
      }
    },
    {
      "hostname": "rlarzronkgoyvtdkltqy.supabase.co",
      "ip": "104.18.27.135",
      "geoip": {
        "registered_country": {
          "geoname_id": 6252001,
          "iso_code": "US",
          "names": {
            "de": "Vereinigte Staaten",
            "en": "United States",
            "es": "Estados Unidos",
            "fr": "États Unis",
            "ja": "アメリカ",
            "pt-BR": "EUA",
            "ru": "США",
            "zh-CN": "美国"
          }
        }
      }
    },
    {
      "hostname": "metrics.userguiding.com",
      "ip": "172.67.70.147",
      "geoip": {
        "continent": {
          "code": "NA",
          "geoname_id": 6255149,
          "names": {
            "de": "Nordamerika",
            "en": "North America",
            "es": "Norteamérica",
            "fr": "Amérique du Nord",
            "ja": "北アメリカ",
            "pt-BR": "América do Norte",
            "ru": "Северная Америка",
            "zh-CN": "北美洲"
          }
        },
        "country": {
          "geoname_id": 6252001,
          "iso_code": "US",
          "names": {
            "de": "Vereinigte Staaten",
            "en": "United States",
            "es": "Estados Unidos",
            "fr": "États Unis",
            "ja": "アメリカ",
            "pt-BR": "EUA",
            "ru": "США",
            "zh-CN": "美国"
          }
        },
        "location": {
          "accuracy_radius": 1000,
          "latitude": 37.751,
          "longitude": -97.822,
          "time_zone": "America/Chicago"
        },
        "registered_country": {
          "geoname_id": 6252001,
          "iso_code": "US",
          "names": {
            "de": "Vereinigte Staaten",
            "en": "United States",
            "es": "Estados Unidos",
            "fr": "États Unis",
            "ja": "アメリカ",
            "pt-BR": "EUA",
            "ru": "США",
            "zh-CN": "美国"
          }
        }
      }
    },
    {
      "hostname": "image.crisp.chat",
      "ip": "104.18.28.91",
      "geoip": {
        "registered_country": {
          "geoname_id": 6252001,
          "iso_code": "US",
          "names": {
            "de": "Vereinigte Staaten",
            "en": "United States",
            "es": "Estados Unidos",
            "fr": "États Unis",
            "ja": "アメリカ",
            "pt-BR": "EUA",
            "ru": "США",
            "zh-CN": "美国"
          }
        }
      }
    }
  ]
}
