{
	"@programName": "OWASP ZAP",
	"@version": "2.12.0",
	"@generated": "Sun, 18 Jun 2023 15:24:18",
	"site":[ 
		{
			"@name": "https://moncompte.snu.gouv.fr",
			"@host": "moncompte.snu.gouv.fr",
			"@port": "443",
			"@ssl": "true",
			"alerts": [ 
				{
					"pluginid": "10038",
					"alertRef": "10038-1",
					"alert": "Content Security Policy (CSP) Header Not Set",
					"name": "Content Security Policy (CSP) Header Not Set",
					"riskcode": "2",
					"confidence": "3",
					"riskdesc": "Medium (High)",
					"desc": "<p>Content Security Policy (CSP) is an added layer of security that helps to detect and mitigate certain types of attacks, including Cross Site Scripting (XSS) and data injection attacks. These attacks are used for everything from data theft to site defacement or distribution of malware. CSP provides a set of standard HTTP headers that allow website owners to declare approved sources of content that browsers should be allowed to load on that page \u2014 covered types are JavaScript, CSS, HTML frames, fonts, images and embeddable objects such as Java applets, ActiveX, audio and video files.</p>",
					"instances":[ 
						{
							"uri": "https://moncompte.snu.gouv.fr",
							"method": "GET",
							"param": "",
							"attack": "",
							"evidence": "",
							"otherinfo": ""
						},
						{
							"uri": "https://moncompte.snu.gouv.fr/robots.txt",
							"method": "GET",
							"param": "",
							"attack": "",
							"evidence": "",
							"otherinfo": ""
						},
						{
							"uri": "https://moncompte.snu.gouv.fr/sitemap.xml",
							"method": "GET",
							"param": "",
							"attack": "",
							"evidence": "",
							"otherinfo": ""
						}
					],
					"count": "3",
					"solution": "<p>Ensure that your web server, application server, load balancer, etc. is configured to set the Content-Security-Policy header.</p>",
					"otherinfo": "",
					"reference": "<p>https://developer.mozilla.org/en-US/docs/Web/Security/CSP/Introducing_Content_Security_Policy</p><p>https://cheatsheetseries.owasp.org/cheatsheets/Content_Security_Policy_Cheat_Sheet.html</p><p>http://www.w3.org/TR/CSP/</p><p>http://w3c.github.io/webappsec/specs/content-security-policy/csp-specification.dev.html</p><p>http://www.html5rocks.com/en/tutorials/security/content-security-policy/</p><p>http://caniuse.com/#feat=contentsecuritypolicy</p><p>http://content-security-policy.com/</p>",
					"cweid": "693",
					"wascid": "15",
					"sourceid": "1"
				},
				{
					"pluginid": "90003",
					"alertRef": "90003",
					"alert": "Sub Resource Integrity Attribute Missing",
					"name": "Sub Resource Integrity Attribute Missing",
					"riskcode": "2",
					"confidence": "3",
					"riskdesc": "Medium (High)",
					"desc": "<p>The integrity attribute is missing on a script or link tag served by an external server. The integrity tag prevents an attacker who have gained access to this server from injecting a malicious content. </p>",
					"instances":[ 
						{
							"uri": "https://moncompte.snu.gouv.fr",
							"method": "GET",
							"param": "",
							"attack": "",
							"evidence": "<link href=\"https://fonts.googleapis.com/css2?family=Roboto:wght@100;400;500&display=swap\"rel=\"stylesheet\">",
							"otherinfo": ""
						},
						{
							"uri": "https://moncompte.snu.gouv.fr/robots.txt",
							"method": "GET",
							"param": "",
							"attack": "",
							"evidence": "<link href=\"https://fonts.googleapis.com/css2?family=Roboto:wght@100;400;500&display=swap\"rel=\"stylesheet\">",
							"otherinfo": ""
						},
						{
							"uri": "https://moncompte.snu.gouv.fr/sitemap.xml",
							"method": "GET",
							"param": "",
							"attack": "",
							"evidence": "<link href=\"https://fonts.googleapis.com/css2?family=Roboto:wght@100;400;500&display=swap\"rel=\"stylesheet\">",
							"otherinfo": ""
						}
					],
					"count": "3",
					"solution": "<p>Provide a valid integrity attribute to the tag.</p>",
					"otherinfo": "",
					"reference": "<p>https://developer.mozilla.org/en/docs/Web/Security/Subresource_Integrity</p>",
					"cweid": "345",
					"wascid": "15",
					"sourceid": "1"
				},
				{
					"pluginid": "10063",
					"alertRef": "10063-1",
					"alert": "Permissions Policy Header Not Set",
					"name": "Permissions Policy Header Not Set",
					"riskcode": "1",
					"confidence": "2",
					"riskdesc": "Low (Medium)",
					"desc": "<p>Permissions Policy Header is an added layer of security that helps to restrict from unauthorized access or usage of browser/client features by web resources. This policy ensures the user privacy by limiting or specifying the features of the browsers can be used by the web resources. Permissions Policy provides a set of standard HTTP headers that allow website owners to limit which features of browsers can be used by the page such as camera, microphone, location, full screen etc.</p>",
					"instances":[ 
						{
							"uri": "https://moncompte.snu.gouv.fr",
							"method": "GET",
							"param": "",
							"attack": "",
							"evidence": "",
							"otherinfo": ""
						},
						{
							"uri": "https://moncompte.snu.gouv.fr/robots.txt",
							"method": "GET",
							"param": "",
							"attack": "",
							"evidence": "",
							"otherinfo": ""
						},
						{
							"uri": "https://moncompte.snu.gouv.fr/sitemap.xml",
							"method": "GET",
							"param": "",
							"attack": "",
							"evidence": "",
							"otherinfo": ""
						}
					],
					"count": "3",
					"solution": "<p>Ensure that your web server, application server, load balancer, etc. is configured to set the Permissions-Policy header.</p>",
					"otherinfo": "",
					"reference": "<p>https://developer.mozilla.org/en-US/docs/Web/HTTP/Headers/Feature-Policy</p><p>https://developers.google.com/web/updates/2018/06/feature-policy</p><p>https://scotthelme.co.uk/a-new-security-header-feature-policy/</p><p>https://w3c.github.io/webappsec-feature-policy/</p><p>https://www.smashingmagazine.com/2018/12/feature-policy/</p>",
					"cweid": "693",
					"wascid": "15",
					"sourceid": "1"
				},
				{
					"pluginid": "10094",
					"alertRef": "10094-3",
					"alert": "Base64 Disclosure",
					"name": "Base64 Disclosure",
					"riskcode": "0",
					"confidence": "2",
					"riskdesc": "Informational (Medium)",
					"desc": "<p>Base64 encoded data was disclosed by the application/web server. Note: in the interests of performance not all base64 strings in the response were analyzed individually, the entire response should be looked at by the analyst/security team/developer(s).</p>",
					"instances":[ 
						{
							"uri": "https://moncompte.snu.gouv.fr",
							"method": "GET",
							"param": "",
							"attack": "",
							"evidence": "wuwWaOUI_laBrCN4kI62gF-jmA_SzcxO01zC8Nd-_eUfYAXgyBkX_CW8LWB6GC1VnJs2OXNOm1xvE5NP3BhG18miZjPzFj3hRfSBIQ1-xCJn07Oqjp7RLk9w6QltuP8X0mvxy70nam4ebFejvCJGmv-vzxTJ6I-S2K2rQTTyDUA0bhcaaAOOb-jqyMXZfFz2AS0W7Xji5EBOQrjv9F_5Og",
							"otherinfo": "\uFFFD\uFFFD\\x0016h\uFFFD\\x0008\uFFFDV\uFFFD\uFFFD#x\uFFFD\uFFFD\uFFFD\uFFFD_\uFFFD\uFFFD\\x000f\uFFFD\uFFFD\uFFFDN\uFFFD\\\uFFFD\uFFFD\uFFFD~\uFFFD\uFFFD\\x001f`\\x0005\uFFFD\uFFFD\\x0019\\x0017\uFFFD%\uFFFD-`z\\x0018-U\uFFFD\uFFFD69sN\uFFFD\\o\\x0013\uFFFDO\uFFFD\\x0018F\uFFFD\u0262f3\uFFFD\\x0016=\uFFFDE\uFFFD!\r~\uFFFD\"g\u04F3\uFFFD\uFFFD\uFFFD\uFFFD.Op\uFFFD\tm\uFFFD\uFFFD\\x0017\uFFFDk\uFFFD\u02FD'jn\\x001elW\uFFFD\uFFFD\"F\uFFFD\uFFFD\uFFFD\uFFFD\\x0014\uFFFD\u83D2\u062D\uFFFDA4\uFFFD\r@4n\\x0017\\x001ah\\x0003\uFFFDo\uFFFD\uFFFD\uFFFD\uFFFD\uFFFD|\\\uFFFD\\x0001-\\x0016\uFFFDx\uFFFD\uFFFD@NB\uFFFD\uFFFD\uFFFD_\uFFFD:"
						},
						{
							"uri": "https://moncompte.snu.gouv.fr",
							"method": "GET",
							"param": "",
							"attack": "",
							"evidence": "mtFwTh8STZXHtE7y8IKjbELzNp_zfcAwdbNC-PZ-XgTPNPBWpmHQiy3LrFB6hg9nBju4qeOkUWWQoo6E9NxQDPo2vq9on9nPasUCo0Wg3CtqNFFb0KtxOui8DaPprLxmgEG8OjlfF8v2R9CO4WRknLJHfoHfzMl5JCmLQbAoEmbMmUqHhQuVz3xaCS5CdwKruGekindk9lGu8qqcGBqOzA",
							"otherinfo": "\uFFFD\uFFFDpN\\x001f\\x0012M\uFFFD\u01F4N\uFFFD\uFFFD\uFFFD\uFFFDlB\uFFFD6\uFFFD\uFFFD}\uFFFD0u\uFFFDB\uFFFD\uFFFD~^\\x0004\uFFFD4\uFFFDV\uFFFDa\u040B-\u02ECPz\uFFFD\\x000fg\\x0006;\uFFFD\uFFFD\uFFFDQe\uFFFD\uFFFD\uFFFD\uFFFD\uFFFD\uFFFDP\\x000c\uFFFD6\uFFFD\uFFFDh\uFFFD\uFFFD\uFFFDj\uFFFD\\x0002\uFFFDE\uFFFD\uFFFD+j4Q[\u042Bq:\uFFFD\r\uFFFD\u9B3Cf\uFFFDA\uFFFD:9_\\x0017\uFFFD\uFFFDG\u040E\uFFFDdd\uFFFD\uFFFDG~\uFFFD\uFFFD\uFFFD\uFFFDy$)\uFFFDA\uFFFD(\\x0012f\u0319J\uFFFD\uFFFD\\x000b\uFFFD\uFFFD|Z\t.Bw\\x0002\uFFFD\uFFFDg\uFFFD\uFFFDwd\uFFFDQ\uFFFD\uFFFD\\x0018\\x001a\uFFFD\uFFFD"
						},
						{
							"uri": "https://moncompte.snu.gouv.fr/robots.txt",
							"method": "GET",
							"param": "",
							"attack": "",
							"evidence": "wuwWaOUI_laBrCN4kI62gBKmymy2MUQW_dKeDyIRTh06QKV35-DhkV8zClhpTeiZS84YyJtxg_ogdKfk89isBgJqm2XYyI5otVLMUuKiUkbEdJnEO6WUE05erHRbKW96Y37dOOhR5RER6lERPsxfA2CDF1iphjYjzrt5lkYYnBLt0hzItD4W5P0j68psk8omB_EgQAfe8W_AnDQSBn9cWQ",
							"otherinfo": "\uFFFD\uFFFD\\x0016h\uFFFD\\x0008\uFFFDV\uFFFD\uFFFD#x\uFFFD\uFFFD\uFFFD\uFFFD\\x0012\uFFFD\uFFFDl\uFFFD1D\\x0016\uFFFD\u049E\\x000f\"\\x0011N\\x001d:@\uFFFDw\uFFFD\uFFFD\uFFFD_3\nXiM\uFFFDK\uFFFD\\x0018\u021Bq\uFFFD\uFFFD t\uFFFD\uFFFD\uFFFD\u062C\\x0006\\x0002j\uFFFDe\uFFFD\u020Eh\uFFFDR\uFFFDR\uFFFDRF\uFFFDt\uFFFD\uFFFD;\uFFFD\uFFFD\\x0013N^\uFFFDt[)ozc~\uFFFD8\uFFFDQ\uFFFD\\x0011\\x0011\uFFFDQ\\x0011>\uFFFD_\\x0003`\uFFFD\\x0017X\uFFFD\uFFFD6#\u03BBy\uFFFDF\\x0018\uFFFD\\x0012\uFFFD\uFFFD\\x001c\u0234>\\x0016\uFFFD\uFFFD#\uFFFD\uFFFDl\uFFFD\uFFFD&\\x0007\uFFFD @\\x0007\uFFFD\uFFFDo\uFFFD\uFFFD4\\x0012\\x0006\\Y"
						},
						{
							"uri": "https://moncompte.snu.gouv.fr/sitemap.xml",
							"method": "GET",
							"param": "",
							"attack": "",
							"evidence": "IEkhQYSoPEgPFLLbiPcNDh2dFULes76vKD4Vnt3HGKi_szYK6hNJEasWuE53dDsF81Hg7D7zWG4DEHDYPloU_zlVyXuPp1--smyKMB-NuQryf9Gi8aMiSH8qqyD5leHeKnpO_bUKGNXQwV6nEdjDtUqb3R6iHIStXizNFGUsJeH5bvbfFrKuxxfpZdTvLEkO819akUAr4Bs7Sv9SepJM4w",
							"otherinfo": " I!A\uFFFD\uFFFD<H\\x000f\\x0014\uFFFD\u06C8\uFFFD\r\\x000e\\x001d\uFFFD\\x0015B\u07B3\uFFFD\uFFFD(>\\x0015\uFFFD\uFFFD\uFFFD\\x0018\uFFFD\uFFFD\uFFFD6\n\uFFFD\\x0013I\\x0011\uFFFD\\x0016\uFFFDNwt;\\x0005\uFFFDQ\uFFFD\uFFFD>\uFFFDXn\\x0003\\x0010p\uFFFD>Z\\x0014\uFFFD9U\uFFFD{\uFFFD\uFFFD_\uFFFD\uFFFDl\uFFFD0\\x001f\uFFFD\uFFFD\n\uFFFD\u0462\uFFFD\"H*\uFFFD \uFFFD\uFFFD\uFFFD\uFFFD*zN\uFFFD\uFFFD\n\\x0018\uFFFD\uFFFD\uFFFD^\uFFFD\\x0011\uFFFD\u00F5J\uFFFD\uFFFD\\x001e\uFFFD\\x001c\uFFFD\uFFFD^,\uFFFD\\x0014e,%\uFFFD\uFFFDn\uFFFD\uFFFD\\x0016\uFFFD\uFFFD\uFFFD\\x0017\uFFFDe\uFFFD\uFFFD,I\\x000e\uFFFD_Z\uFFFD@+\uFFFD\\x001b;J\uFFFDRz\uFFFDL\uFFFD"
						}
					],
					"count": "4",
					"solution": "<p>Manually confirm that the Base64 data does not leak sensitive information, and that the data cannot be aggregated/used to exploit other vulnerabilities.</p>",
					"otherinfo": "<p>\uFFFD\uFFFD\\x0016h\uFFFD\\x0008\uFFFDV\uFFFD\uFFFD#x\uFFFD\uFFFD\uFFFD\uFFFD_\uFFFD\uFFFD\\x000f\uFFFD\uFFFD\uFFFDN\uFFFD\\\uFFFD\uFFFD\uFFFD~\uFFFD\uFFFD\\x001f`\\x0005\uFFFD\uFFFD\\x0019\\x0017\uFFFD%\uFFFD-`z\\x0018-U\uFFFD\uFFFD69sN\uFFFD\\o\\x0013\uFFFDO\uFFFD\\x0018F\uFFFD\u0262f3\uFFFD\\x0016=\uFFFDE\uFFFD!\r~\uFFFD\"g\u04F3\uFFFD\uFFFD\uFFFD\uFFFD.Op\uFFFD\tm\uFFFD\uFFFD\\x0017\uFFFDk\uFFFD\u02FD'jn\\x001elW\uFFFD\uFFFD\"F\uFFFD\uFFFD\uFFFD\uFFFD\\x0014\uFFFD\u83D2\u062D\uFFFDA4\uFFFD\r@4n\\x0017\\x001ah\\x0003\uFFFDo\uFFFD\uFFFD\uFFFD\uFFFD\uFFFD|\\\uFFFD\\x0001-\\x0016\uFFFDx\uFFFD\uFFFD@NB\uFFFD\uFFFD\uFFFD_\uFFFD:</p>",
					"reference": "<p>http://projects.webappsec.org/w/page/13246936/Information%20Leakage</p>",
					"cweid": "200",
					"wascid": "13",
					"sourceid": "8"
				},
				{
					"pluginid": "10109",
					"alertRef": "10109",
					"alert": "Modern Web Application",
					"name": "Modern Web Application",
					"riskcode": "0",
					"confidence": "2",
					"riskdesc": "Informational (Medium)",
					"desc": "<p>The application appears to be a modern web application. If you need to explore it automatically then the Ajax Spider may well be more effective than the standard one.</p>",
					"instances":[ 
						{
							"uri": "https://moncompte.snu.gouv.fr",
							"method": "GET",
							"param": "",
							"attack": "",
							"evidence": "<noscript><div class=\"challengejs-container\"><div class=\"container\"><div class=\"challengejs-body\"><div class=\"challengejs-card\"><img src=\"/.well-known/baleen/challengejs/assets/logo.svg\"><div class=\"challengejs-message-1\">Le JavaScript n'est pas activ\u00E9 sur votre navigateur.</div><div class=\"separator\"></div><div class=\"challengejs-message-2\">Le JavaScript n'est pas activ\u00E9 sur votre navigateur. Pour vous permettre de naviguer correctement sur notre site, il est n\u00E9cessaire qu'il soit activ\u00E9.</div><div class=\"challengejs-message-3\"><div class=\"how\"><span>Comment activer le JavaScript ?</span></div><div class=\"drop\"><div class=\"how-to chrome\"><div>Chrome</div><a href=\"https://support.google.com/chrome\">https://support.google.com/chrome</a></div><div class=\"how-to firefox\"><div>Mozilla Firefox</div><a href=\"https://support.mozilla.org/fr/home\">https://support.mozilla.org/fr/home</a></div><div class=\"how-to safari\"><div>Safari</div><a href=\"https://www.apple.com/support/safari/\">https://www.apple.com/support/safari/</a></div><div class=\"how-to opera\"><div>Opera</div><a href=\"https://support.google.com/adsense/answer/12654?hl=fr\">https://support.google.com/adsense/answer/12654?hl=fr</a></div><div class=\"how-to explorer\"><div>Internet Explorer</div><a href=\"https://support.microsoft.com/product/internet-explorer\">https://support.microsoft.com/product/internet-explorer</a></div></div></div></div></div></div></div></noscript>",
							"otherinfo": "A noScript tag has been found, which is an indication that the application works differently with JavaScript enabled compared to when it is not."
						},
						{
							"uri": "https://moncompte.snu.gouv.fr/robots.txt",
							"method": "GET",
							"param": "",
							"attack": "",
							"evidence": "<noscript><div class=\"challengejs-container\"><div class=\"container\"><div class=\"challengejs-body\"><div class=\"challengejs-card\"><img src=\"/.well-known/baleen/challengejs/assets/logo.svg\"><div class=\"challengejs-message-1\">Le JavaScript n'est pas activ\u00E9 sur votre navigateur.</div><div class=\"separator\"></div><div class=\"challengejs-message-2\">Le JavaScript n'est pas activ\u00E9 sur votre navigateur. Pour vous permettre de naviguer correctement sur notre site, il est n\u00E9cessaire qu'il soit activ\u00E9.</div><div class=\"challengejs-message-3\"><div class=\"how\"><span>Comment activer le JavaScript ?</span></div><div class=\"drop\"><div class=\"how-to chrome\"><div>Chrome</div><a href=\"https://support.google.com/chrome\">https://support.google.com/chrome</a></div><div class=\"how-to firefox\"><div>Mozilla Firefox</div><a href=\"https://support.mozilla.org/fr/home\">https://support.mozilla.org/fr/home</a></div><div class=\"how-to safari\"><div>Safari</div><a href=\"https://www.apple.com/support/safari/\">https://www.apple.com/support/safari/</a></div><div class=\"how-to opera\"><div>Opera</div><a href=\"https://support.google.com/adsense/answer/12654?hl=fr\">https://support.google.com/adsense/answer/12654?hl=fr</a></div><div class=\"how-to explorer\"><div>Internet Explorer</div><a href=\"https://support.microsoft.com/product/internet-explorer\">https://support.microsoft.com/product/internet-explorer</a></div></div></div></div></div></div></div></noscript>",
							"otherinfo": "A noScript tag has been found, which is an indication that the application works differently with JavaScript enabled compared to when it is not."
						},
						{
							"uri": "https://moncompte.snu.gouv.fr/sitemap.xml",
							"method": "GET",
							"param": "",
							"attack": "",
							"evidence": "<noscript><div class=\"challengejs-container\"><div class=\"container\"><div class=\"challengejs-body\"><div class=\"challengejs-card\"><img src=\"/.well-known/baleen/challengejs/assets/logo.svg\"><div class=\"challengejs-message-1\">Le JavaScript n'est pas activ\u00E9 sur votre navigateur.</div><div class=\"separator\"></div><div class=\"challengejs-message-2\">Le JavaScript n'est pas activ\u00E9 sur votre navigateur. Pour vous permettre de naviguer correctement sur notre site, il est n\u00E9cessaire qu'il soit activ\u00E9.</div><div class=\"challengejs-message-3\"><div class=\"how\"><span>Comment activer le JavaScript ?</span></div><div class=\"drop\"><div class=\"how-to chrome\"><div>Chrome</div><a href=\"https://support.google.com/chrome\">https://support.google.com/chrome</a></div><div class=\"how-to firefox\"><div>Mozilla Firefox</div><a href=\"https://support.mozilla.org/fr/home\">https://support.mozilla.org/fr/home</a></div><div class=\"how-to safari\"><div>Safari</div><a href=\"https://www.apple.com/support/safari/\">https://www.apple.com/support/safari/</a></div><div class=\"how-to opera\"><div>Opera</div><a href=\"https://support.google.com/adsense/answer/12654?hl=fr\">https://support.google.com/adsense/answer/12654?hl=fr</a></div><div class=\"how-to explorer\"><div>Internet Explorer</div><a href=\"https://support.microsoft.com/product/internet-explorer\">https://support.microsoft.com/product/internet-explorer</a></div></div></div></div></div></div></div></noscript>",
							"otherinfo": "A noScript tag has been found, which is an indication that the application works differently with JavaScript enabled compared to when it is not."
						}
					],
					"count": "3",
					"solution": "<p>This is an informational alert and so no changes are required.</p>",
					"otherinfo": "<p>A noScript tag has been found, which is an indication that the application works differently with JavaScript enabled compared to when it is not.</p>",
					"reference": "",
					"cweid": "-1",
					"wascid": "-1",
					"sourceid": "1"
				},
				{
					"pluginid": "10015",
					"alertRef": "10015",
					"alert": "Re-examine Cache-control Directives",
					"name": "Re-examine Cache-control Directives",
					"riskcode": "0",
					"confidence": "1",
					"riskdesc": "Informational (Low)",
					"desc": "<p>The cache-control header has not been set properly or is missing, allowing the browser and proxies to cache content. For static assets like css, js, or image files this might be intended, however, the resources should be reviewed to ensure that no sensitive content will be cached.</p>",
					"instances":[ 
						{
							"uri": "https://moncompte.snu.gouv.fr",
							"method": "GET",
							"param": "Cache-Control",
							"attack": "",
							"evidence": "no-cache",
							"otherinfo": ""
						},
						{
							"uri": "https://moncompte.snu.gouv.fr/robots.txt",
							"method": "GET",
							"param": "Cache-Control",
							"attack": "",
							"evidence": "no-cache",
							"otherinfo": ""
						},
						{
							"uri": "https://moncompte.snu.gouv.fr/sitemap.xml",
							"method": "GET",
							"param": "Cache-Control",
							"attack": "",
							"evidence": "no-cache",
							"otherinfo": ""
						}
					],
					"count": "3",
					"solution": "<p>For secure content, ensure the cache-control HTTP header is set with \"no-cache, no-store, must-revalidate\". If an asset should be cached consider setting the directives \"public, max-age, immutable\".</p>",
					"otherinfo": "",
					"reference": "<p>https://cheatsheetseries.owasp.org/cheatsheets/Session_Management_Cheat_Sheet.html#web-content-caching</p><p>https://developer.mozilla.org/en-US/docs/Web/HTTP/Headers/Cache-Control</p><p>https://grayduck.mn/2021/09/13/cache-control-recommendations/</p>",
					"cweid": "525",
					"wascid": "13",
					"sourceid": "1"
				},
				{
					"pluginid": "10049",
					"alertRef": "10049",
					"alert": "Storable and Cacheable Content",
					"name": "Storable and Cacheable Content",
					"riskcode": "0",
					"confidence": "2",
					"riskdesc": "Informational (Medium)",
					"desc": "<p>The response contents are storable by caching components such as proxy servers, and may be retrieved directly from the cache, rather than from the origin server by the caching servers, in response to similar requests from other users.  If the response data is sensitive, personal or user-specific, this may result in sensitive information being leaked. In some cases, this may even result in a user gaining complete control of the session of another user, depending on the configuration of the caching components in use in their environment. This is primarily an issue where \"shared\" caching servers such as \"proxy\" caches are configured on the local network. This configuration is typically found in corporate or educational environments, for instance.</p>",
					"instances":[ 
						{
							"uri": "https://moncompte.snu.gouv.fr/.well-known/baleen/challengejs/assets/logo.svg",
							"method": "GET",
							"param": "",
							"attack": "",
							"evidence": "",
							"otherinfo": "In the absence of an explicitly specified caching lifetime directive in the response, a liberal lifetime heuristic of 1 year was assumed. This is permitted by rfc7234."
						},
						{
							"uri": "https://moncompte.snu.gouv.fr/.well-known/baleen/challengejs/assets/style.css",
							"method": "GET",
							"param": "",
							"attack": "",
							"evidence": "",
							"otherinfo": "In the absence of an explicitly specified caching lifetime directive in the response, a liberal lifetime heuristic of 1 year was assumed. This is permitted by rfc7234."
						}
					],
					"count": "2",
					"solution": "<p>Validate that the response does not contain sensitive, personal or user-specific information.  If it does, consider the use of the following HTTP response headers, to limit, or prevent the content being stored and retrieved from the cache by another user:</p><p>Cache-Control: no-cache, no-store, must-revalidate, private</p><p>Pragma: no-cache</p><p>Expires: 0</p><p>This configuration directs both HTTP 1.0 and HTTP 1.1 compliant caching servers to not store the response, and to not retrieve the response (without validation) from the cache, in response to a similar request. </p>",
					"otherinfo": "<p>In the absence of an explicitly specified caching lifetime directive in the response, a liberal lifetime heuristic of 1 year was assumed. This is permitted by rfc7234.</p>",
					"reference": "<p>https://tools.ietf.org/html/rfc7234</p><p>https://tools.ietf.org/html/rfc7231</p><p>http://www.w3.org/Protocols/rfc2616/rfc2616-sec13.html (obsoleted by rfc7234)</p>",
					"cweid": "524",
					"wascid": "13",
					"sourceid": "16"
				},
				{
					"pluginid": "10049",
					"alertRef": "10049",
					"alert": "Storable but Non-Cacheable Content",
					"name": "Storable but Non-Cacheable Content",
					"riskcode": "0",
					"confidence": "2",
					"riskdesc": "Informational (Medium)",
					"desc": "<p>The response contents are storable by caching components such as proxy servers, but will not be retrieved directly from the cache, without validating the request upstream, in response to similar requests from other users. </p>",
					"instances":[ 
						{
							"uri": "https://moncompte.snu.gouv.fr",
							"method": "GET",
							"param": "",
							"attack": "",
							"evidence": "no-cache",
							"otherinfo": ""
						},
						{
							"uri": "https://moncompte.snu.gouv.fr/robots.txt",
							"method": "GET",
							"param": "",
							"attack": "",
							"evidence": "no-cache",
							"otherinfo": ""
						},
						{
							"uri": "https://moncompte.snu.gouv.fr/sitemap.xml",
							"method": "GET",
							"param": "",
							"attack": "",
							"evidence": "no-cache",
							"otherinfo": ""
						}
					],
					"count": "3",
					"solution": "",
					"otherinfo": "",
					"reference": "<p>https://tools.ietf.org/html/rfc7234</p><p>https://tools.ietf.org/html/rfc7231</p><p>http://www.w3.org/Protocols/rfc2616/rfc2616-sec13.html (obsoleted by rfc7234)</p>",
					"cweid": "524",
					"wascid": "13",
					"sourceid": "1"
				}
			]
		}
	]
}
