{
  "trackers": [],
  "cookies": [
    {
      "name": "_pk_ses.27.0c8d",
      "value": "1",
      "domain": "aplypro.beta.gouv.fr",
      "path": "/",
      "expires": 1701647468,
      "size": 16,
      "httpOnly": false,
      "secure": false,
      "session": false,
      "sameSite": "Lax",
      "sameParty": false,
      "sourceScheme": "Secure",
      "sourcePort": 443
    },
    {
      "name": "_pk_id.27.0c8d",
      "value": "2f1f1d29bb2ef68c.1701645669.",
      "domain": "aplypro.beta.gouv.fr",
      "path": "/",
      "expires": 1735600869,
      "size": 42,
      "httpOnly": false,
      "secure": false,
      "session": false,
      "sameSite": "Lax",
      "sameParty": false,
      "sourceScheme": "Secure",
      "sourcePort": 443
    },
    {
      "name": "_aplypro_session",
      "value": "XKyUKmAZU%2FjrwzseqbmNAMQYyLDmkhVk2ru%2FIi8olCcJpk1Mh6InQ9pQ818urXFqAxG8Gx%2FW6mkhOPrEhaHrroPadPBTJOc1RfBtxzAThuO6KcCezdPsDKvQ4%2BZrmav9oWMiKVwP6VzU4d4r0MyjNJg5DopyOmAE2Gk9A0Io8klqx6tsuqqz1P8MRUyuCPbvBdrM8VUSwrFb9LHa2gRhLuGReBXKmQ97lD%2FGWSb1PkYeZhZ3ect6adYzhMiGHW%2B64wBhYpGqRnGVBKH5guWm83y4bVmv1eNB--H54okRrjVsvEoTgk--Ig%2BlrOGYvoimT2yh8hCeeA%3D%3D",
      "domain": "aplypro.beta.gouv.fr",
      "path": "/",
      "expires": -1,
      "size": 366,
      "httpOnly": true,
      "secure": false,
      "session": true,
      "sameSite": "Lax",
      "sameParty": false,
      "sourceScheme": "Secure",
      "sourcePort": 443
    }
  ],
  "headers": {
    "cache-control": "max-age=0, private, must-revalidate",
    "content-encoding": "gzip",
    "content-type": "text/html; charset=utf-8",
    "date": "Sun, 03 Dec 2023 23:21:07 GMT",
    "etag": "W/\"7c2ea46047955481dcf4c15c06b56d95\"",
    "link": "</assets/dsfr.min-f992b45e5939c1a33e196ebc6a905a09d963d3dbe76551c12224a249a90a3954.css>; rel=preload; as=style; nopush,</assets/application-6b0b379f2e996a3680a7a72d058f3ad4b0bf1f5233c70a81520006ecaeeae536.css>; rel=preload; as=style; nopush,</assets/dsfr.module.min-d9d68f7bbb91db7d326936821d66698a4b7389230694648fe655aa9c6c3a6585.js>; rel=modulepreload; as=script; nopush,</assets/dsfr.nomodule.min-8d58c5010e1e36751766486cc8e3bc8b5b4b45cbe22aae23084c76dc49b989ff.js>; rel=preload; as=script; nopush,</assets/es-module-shims.min-4ca9b3dd5e434131e3bb4b0c1d7dff3bfd4035672a5086deec6f73979a49be73.js>; rel=preload; as=script; nopush",
    "referrer-policy": "strict-origin-when-cross-origin",
    "set-cookie": "_aplypro_session=XKyUKmAZU%2FjrwzseqbmNAMQYyLDmkhVk2ru%2FIi8olCcJpk1Mh6InQ9pQ818urXFqAxG8Gx%2FW6mkhOPrEhaHrroPadPBTJOc1RfBtxzAThuO6KcCezdPsDKvQ4%2BZrmav9oWMiKVwP6VzU4d4r0MyjNJg5DopyOmAE2Gk9A0Io8klqx6tsuqqz1P8MRUyuCPbvBdrM8VUSwrFb9LHa2gRhLuGReBXKmQ97lD%2FGWSb1PkYeZhZ3ect6adYzhMiGHW%2B64wBhYpGqRnGVBKH5guWm83y4bVmv1eNB--H54okRrjVsvEoTgk--Ig%2BlrOGYvoimT2yh8hCeeA%3D%3D; path=/; HttpOnly; SameSite=Lax",
    "strict-transport-security": "max-age=31536000",
    "x-content-type-options": "nosniff",
    "x-frame-options": "SAMEORIGIN",
    "x-permitted-cross-domain-policies": "none",
    "x-request-id": "9ef2177a-0f6b-46a8-aa4e-2e6c628c0f4b\n9ef2177a-0f6b-46a8-aa4e-2e6c628c0f4b",
    "x-runtime": "0.009887",
    "x-xss-protection": "0"
  },
  "endpoints": [
    {
      "hostname": "aplypro.beta.gouv.fr",
      "ip": "80.247.13.145",
      "geoip": {
        "continent": {
          "code": "EU",
          "geoname_id": 6255148,
          "names": {
            "de": "Europa",
            "en": "Europe",
            "es": "Europa",
            "fr": "Europe",
            "ja": "ヨーロッパ",
            "pt-BR": "Europa",
            "ru": "Европа",
            "zh-CN": "欧洲"
          }
        },
        "country": {
          "geoname_id": 3017382,
          "is_in_european_union": true,
          "iso_code": "FR",
          "names": {
            "de": "Frankreich",
            "en": "France",
            "es": "Francia",
            "fr": "France",
            "ja": "フランス共和国",
            "pt-BR": "França",
            "ru": "Франция",
            "zh-CN": "法国"
          }
        },
        "location": {
          "accuracy_radius": 500,
          "latitude": 48.8582,
          "longitude": 2.3387,
          "time_zone": "Europe/Paris"
        },
        "registered_country": {
          "geoname_id": 3017382,
          "is_in_european_union": true,
          "iso_code": "FR",
          "names": {
            "de": "Frankreich",
            "en": "France",
            "es": "Francia",
            "fr": "France",
            "ja": "フランス共和国",
            "pt-BR": "França",
            "ru": "Франция",
            "zh-CN": "法国"
          }
        }
      }
    }
  ]
}
