{
  "id": "données-et-territoires",
  "type": "startup",
  "attributes": {
    "name": "Données et territoires",
    "pitch": "Outiller et accompagner les agents publics dans leurs usages de la donnée",
    "link": "https://donnees.incubateur.anct.gouv.fr",
    "repository": "https://datahub.incubateur.tech/infrastructure/",
    "contact": "donnees@anct.gouv.fr",
    "content_url_encoded_markdown": "%23%23%20C%E2%80%99est%20quoi%20Donn%C3%A9es%20et%20Territoires%20%3F%0A%0AUne%20%2A%2Abo%C3%AEte%20%C3%A0%20outils%20%C3%A9volutive%2A%2A%20constitu%C3%A9e%20d%E2%80%99outils%20pr%C3%A9existants%2C%20adapt%C3%A9s%20ou%20d%C3%A9velopp%C3%A9s%20par%20nos%20soins%20r%C3%A9pondant%20aux%20besoins%20en%20manipulations%20de%20donn%C3%A9es%20des%20collectivit%C3%A9s%20et%20de%20l%E2%80%99ANCT.%0A%0A%2A%2AUn%20guichet%20donn%C3%A9es%2A%2A%20%3A%20une%20%C3%A9quipe%20d%C3%A9di%C3%A9e%2C%20%C3%A0%20l%E2%80%99%C3%A9coute%20des%20besoins%20et%20pilotant%20la%20mise%20en%20place%20de%20la%20bo%C3%AEte%20%C3%A0%20outils.%20Sollicitez-le%20si%20vous%20avez%20un%20besoin%20non-couvert%20par%20la%20bo%C3%AEte%20%C3%A0%20outils.%20%5BNous%20contacter%5D%0A%0A%23%23%20Pourquoi%20Donn%C3%A9es%20et%20Territoires%20%3F%0A%0AL%E2%80%99ANCT%2C%20missionn%C3%A9e%20par%20le%20rapport%20Bothorel%20pour%20%C2%AB%20accompagner%20les%20collectivit%C3%A9s%20territoriales%20dans%20la%20publication%20des%20donn%C3%A9es%20%C2%BB%2C%20au%20cours%20de%20ses%20diff%C3%A9rentes%20investigations%2C%20a%20rencontr%C3%A9%20de%20nombreuses%20probl%C3%A9matiques%20li%C3%A9es%20%C3%A0%20l%E2%80%99utilisation%20des%20donn%C3%A9es%20%3A%0A%0AIl%20y%20a%20une%20forte%20attente%20vis-%C3%A0-vis%20des%20collectivit%C3%A9s%20territoriales%20pour%20ouvrir%20et%20partager%20les%20donn%C3%A9es%20li%C3%A9es%20%C3%A0%20leurs%20activit%C3%A9s%2C%20mais%20souvent%20un%20manque%20de%20moyen%20humain%20et%20technique%20pour%20y%20r%C3%A9pondre%20au%20sein%20des%20collectivit%C3%A9s%0A%0ADe%20m%C3%AAme%2C%20les%20collectivit%C3%A9s%20territoriales%20elles-m%C3%AAmes%20sont%20demandeuses%20d%E2%80%99utilisation%20des%20donn%C3%A9es%20pour%20mieux%20r%C3%A9pondre%20%C3%A0%20leurs%20missions%2C%20sans%20avoir%20l%C3%A0%20non%20plus%20toujours%20les%20moyens%20humains%20et%20techniques%20pour%20le%20faire%0A%0ALa%20manipulation%20de%20donn%C3%A9es%20se%20fait%20souvent%20aujourd%E2%80%99hui%20de%20fa%C3%A7on%20isol%C3%A9e%20%28fichiers%20Excel%20sur%20le%20poste%20d%E2%80%99un%20agent%29%2C%20ayant%20pour%20cons%C3%A9quence%20une%20grande%20perte%20de%20temps%20dans%20le%20traitement%20de%20ces%20donn%C3%A9es%20%3A%20fichiers%20non%20normalis%C3%A9s%20donc%20beaucoup%20d%E2%80%99erreurs%2C%20difficile%20%C3%A0%20partager%2C%20%C3%A0%20mettre%20%C3%A0%20jour%2C%20etc.%0A%0ATr%C3%A8s%20souvent%2C%20les%20agents%20doivent%20saisir%20de%20la%20donn%C3%A9e%20pour%20un%20autre%20usage%20que%20le%20leur%2C%20ce%20qui%20est%20une%20perte%20de%20temps%20et%20un%20motif%20de%20frustration%2C%20par%20ailleurs%20la%20donn%C3%A9e%20qu%E2%80%99on%20saisit%20sans%20en%20comprendre%20la%20finalit%C3%A9%20est%20souvent%20mal%20saisie%0A%0ADonn%C3%A9es%20et%20Territoires%20a%20donc%20pour%20vocation%20d%E2%80%99aider%20ces%20diff%C3%A9rentes%20collectivit%C3%A9s%20territoriales%20pour%20r%C3%A9pondre%20%C3%A0%20leurs%20missions%2C%20en%20construisant%20une%20bo%C3%AEte%20%C3%A0%20outils%20adapt%C3%A9e%20aux%20diff%C3%A9rentes%20collectivit%C3%A9s%20%28de%20la%20petite%20commune%20de%20la%20Creuse%20jusqu%E2%80%99%C3%A0%20la%20M%C3%A9tropole%20de%20Lyon%29.%0A",
    "events": [],
    "phases": [
      {
        "name": "investigation",
        "start": "2021-07-01",
        "end": "2022-01-01"
      },
      {
        "name": "construction",
        "start": "2022-01-01",
        "end": ""
      }
    ]
  },
  "relationships": {
    "incubator": {
      "data": {
        "type": "incubator",
        "id": "anct"
      }
    }
  }
}
