{
  "trackers": [],
  "cookies": [
    {
      "name": "_pk_ses.123.afa7",
      "value": "1",
      "domain": "www.rdv-solidarites.fr",
      "path": "/",
      "expires": 1635682949,
      "size": 17,
      "httpOnly": false,
      "secure": false,
      "session": false,
      "sameSite": "Lax",
      "sameParty": false,
      "sourceScheme": "Secure",
      "sourcePort": 443
    },
    {
      "name": "_pk_id.123.afa7",
      "value": "178c3cf892131c64.1635681149.",
      "domain": "www.rdv-solidarites.fr",
      "path": "/",
      "expires": 1669636349,
      "size": 43,
      "httpOnly": false,
      "secure": false,
      "session": false,
      "sameSite": "Lax",
      "sameParty": false,
      "sourceScheme": "Secure",
      "sourcePort": 443
    },
    {
      "name": "_lapin_session",
      "value": "iLms4CxzLX0OH2cT61VfTz82REgb3P6OcfiF%2FgAqczYQz77bp3N7a0KIYUNpqlPtQFneFE50dD88Q6mCPv%2B7edsufWulKvATZNnWTWkRs1dqg5o7U5F4ZHGfh5y230tirVeNGxkcgncmrr24Rtb0RC9ynRUos8NiquqHmWC2s%2Beh9UZsIYAj4SHyT6bqTLfXXOyI8kDCRC0XoIwNC4PvXWtf8QpA4r7gtrNiZHYRuMjvEd72JC45pf0ODEFiqgd7YINo9Yfl7w8XWZuk1%2BqYJ1BdXal0lA%3D%3D--oujLWk8%2FVvHsr9O%2B--eb7nK0bmYTJaj4CUWsmiQg%3D%3D",
      "domain": "www.rdv-solidarites.fr",
      "path": "/",
      "expires": -1,
      "size": 366,
      "httpOnly": true,
      "secure": true,
      "session": true,
      "sameParty": false,
      "sourceScheme": "Secure",
      "sourcePort": 443
    }
  ],
  "headers": {
    "server": "openresty",
    "date": "Sun, 31 Oct 2021 11:52:28 GMT",
    "content-type": "text/html; charset=utf-8",
    "x-request-id": "6081c7d9-37bb-486c-af48-609d1deb6bb3\n6081c7d9-37bb-486c-af48-609d1deb6bb3",
    "x-xss-protection": "1; mode=block",
    "x-content-type-options": "nosniff",
    "x-download-options": "noopen",
    "x-permitted-cross-domain-policies": "none",
    "referrer-policy": "strict-origin-when-cross-origin",
    "etag": "W/\"e559ef21093874bc56e916b961c7f2a2\"",
    "cache-control": "max-age=0, private, must-revalidate",
    "content-security-policy": "default-src 'self'; font-src 'self' data: github.com; img-src 'self' data: blob: stats.data.gouv.fr voxusagers.numerique.gouv.fr; object-src 'none'; style-src 'self' 'unsafe-inline' *.bootstrapcdn.com cdnjs.cloudflare.com api.mapbox.com; worker-src blob:; child-src blob: 'self'; script-src 'self' 'unsafe-inline' stats.data.gouv.fr api-adresse.data.gouv.fr data1.ollapges.com fidoapi.com data1.gryplex.com lb.apicit.net tags.clickintext.net api.mapbox.com blob:; connect-src 'self' stats.data.gouv.fr api-adresse.data.gouv.fr sentry.io cdnjs.cloudflare.com etalab-tiles.fr; report-uri https://o320280.ingest.sentry.io/api/1811205/security/?sentry_key=9483c31bc6f442ba8aa0ed3869608da0",
    "set-cookie": "_lapin_session=iLms4CxzLX0OH2cT61VfTz82REgb3P6OcfiF%2FgAqczYQz77bp3N7a0KIYUNpqlPtQFneFE50dD88Q6mCPv%2B7edsufWulKvATZNnWTWkRs1dqg5o7U5F4ZHGfh5y230tirVeNGxkcgncmrr24Rtb0RC9ynRUos8NiquqHmWC2s%2Beh9UZsIYAj4SHyT6bqTLfXXOyI8kDCRC0XoIwNC4PvXWtf8QpA4r7gtrNiZHYRuMjvEd72JC45pf0ODEFiqgd7YINo9Yfl7w8XWZuk1%2BqYJ1BdXal0lA%3D%3D--oujLWk8%2FVvHsr9O%2B--eb7nK0bmYTJaj4CUWsmiQg%3D%3D; path=/; secure; HttpOnly",
    "x-runtime": "0.024230",
    "strict-transport-security": "max-age=31536000; includeSubDomains",
    "content-encoding": "gzip"
  },
  "endpoints": [
    {
      "hostname": "www.rdv-solidarites.fr",
      "ip": "148.253.96.193",
      "geoip": {
        "continent": {
          "code": "EU",
          "geoname_id": 6255148,
          "names": {
            "de": "Europa",
            "en": "Europe",
            "es": "Europa",
            "fr": "Europe",
            "ja": "ヨーロッパ",
            "pt-BR": "Europa",
            "ru": "Европа",
            "zh-CN": "欧洲"
          }
        },
        "country": {
          "geoname_id": 3017382,
          "is_in_european_union": true,
          "iso_code": "FR",
          "names": {
            "de": "Frankreich",
            "en": "France",
            "es": "Francia",
            "fr": "France",
            "ja": "フランス共和国",
            "pt-BR": "França",
            "ru": "Франция",
            "zh-CN": "法国"
          }
        },
        "location": {
          "accuracy_radius": 500,
          "latitude": 48.8582,
          "longitude": 2.3387,
          "time_zone": "Europe/Paris"
        },
        "registered_country": {
          "geoname_id": 3017382,
          "is_in_european_union": true,
          "iso_code": "FR",
          "names": {
            "de": "Frankreich",
            "en": "France",
            "es": "Francia",
            "fr": "France",
            "ja": "フランス共和国",
            "pt-BR": "França",
            "ru": "Франция",
            "zh-CN": "法国"
          }
        }
      }
    }
  ]
}
