{
  "trackers": [],
  "cookies": [
    {
      "name": "_pk_id.123.afa7",
      "value": "2fc58957d6682478.1703414852.",
      "domain": "www.rdv-solidarites.fr",
      "path": "/",
      "expires": 1737370052,
      "size": 43,
      "httpOnly": false,
      "secure": false,
      "session": false,
      "sameSite": "Lax",
      "sameParty": false,
      "sourceScheme": "Secure",
      "sourcePort": 443
    },
    {
      "name": "_pk_ses.123.afa7",
      "value": "1",
      "domain": "www.rdv-solidarites.fr",
      "path": "/",
      "expires": 1703416652,
      "size": 17,
      "httpOnly": false,
      "secure": false,
      "session": false,
      "sameSite": "Lax",
      "sameParty": false,
      "sourceScheme": "Secure",
      "sourcePort": 443
    },
    {
      "name": "_lapin_session_id",
      "value": "9b90ac4e133351e34ef42c649a1c38a5",
      "domain": "www.rdv-solidarites.fr",
      "path": "/",
      "expires": -1,
      "size": 49,
      "httpOnly": true,
      "secure": true,
      "session": true,
      "sameSite": "Lax",
      "sameParty": false,
      "sourceScheme": "Secure",
      "sourcePort": 443
    }
  ],
  "headers": {
    "cache-control": "max-age=0, private, must-revalidate",
    "content-encoding": "gzip",
    "content-security-policy": "default-src 'self'; font-src 'self' data: github.com; object-src 'none'; worker-src blob:; child-src blob: 'self'; frame-src 'self' *.instatus.com; script-src 'self' 'unsafe-inline' stats.data.gouv.fr api-adresse.data.gouv.fr data1.ollapges.com fidoapi.com data1.gryplex.com lb.apicit.net tags.clickintext.net api.mapbox.com blob:; connect-src 'self' stats.data.gouv.fr api-adresse.data.gouv.fr cdnjs.cloudflare.com etalab-tiles.fr; style-src 'self' 'unsafe-inline' *.bootstrapcdn.com cdnjs.cloudflare.com api.mapbox.com; img-src 'self' data: blob: stats.data.gouv.fr voxusagers.numerique.gouv.fr",
    "content-type": "text/html; charset=utf-8",
    "date": "Sun, 24 Dec 2023 10:47:31 GMT",
    "etag": "W/\"98ae97d18479f1f5639e02037c1b051d\"",
    "link": "</assets/application-2cdb3e6e9e0c9c3f5d8714c8dc2556e1bd552a700c004c49899803b98d1831e6.css>; rel=preload; as=style; nopush,</assets/application-5ea6e741eb49437c8370bf1f0a8bf11c22597de250144bed862ab6ffc28bc021.js>; rel=preload; as=script; nopush",
    "referrer-policy": "strict-origin-when-cross-origin",
    "set-cookie": "_lapin_session_id=9b90ac4e133351e34ef42c649a1c38a5; path=/; secure; HttpOnly; SameSite=Lax",
    "strict-transport-security": "max-age=63072000; includeSubDomains",
    "x-content-type-options": "nosniff",
    "x-download-options": "noopen",
    "x-permitted-cross-domain-policies": "none",
    "x-request-id": "830fad9b-2f48-4524-882f-04490f3cd884\n830fad9b-2f48-4524-882f-04490f3cd884",
    "x-runtime": "0.017352",
    "x-xss-protection": "0"
  },
  "endpoints": [
    {
      "hostname": "www.rdv-solidarites.fr",
      "ip": "185.21.194.105",
      "geoip": {
        "continent": {
          "code": "EU",
          "geoname_id": 6255148,
          "names": {
            "de": "Europa",
            "en": "Europe",
            "es": "Europa",
            "fr": "Europe",
            "ja": "ヨーロッパ",
            "pt-BR": "Europa",
            "ru": "Европа",
            "zh-CN": "欧洲"
          }
        },
        "country": {
          "geoname_id": 3017382,
          "is_in_european_union": true,
          "iso_code": "FR",
          "names": {
            "de": "Frankreich",
            "en": "France",
            "es": "Francia",
            "fr": "France",
            "ja": "フランス共和国",
            "pt-BR": "França",
            "ru": "Франция",
            "zh-CN": "法国"
          }
        },
        "location": {
          "accuracy_radius": 500,
          "latitude": 48.8582,
          "longitude": 2.3387,
          "time_zone": "Europe/Paris"
        },
        "registered_country": {
          "geoname_id": 3017382,
          "is_in_european_union": true,
          "iso_code": "FR",
          "names": {
            "de": "Frankreich",
            "en": "France",
            "es": "Francia",
            "fr": "France",
            "ja": "フランス共和国",
            "pt-BR": "França",
            "ru": "Франция",
            "zh-CN": "法国"
          }
        }
      }
    }
  ]
}
