{
  "trackers": [],
  "cookies": [],
  "headers": {
    "alt-svc": "h3=\":443\"; ma=86400, h3-29=\":443\"; ma=86400",
    "cf-cache-status": "DYNAMIC",
    "cf-ray": "770b855d6c7d81cd-IAD",
    "content-encoding": "br",
    "content-type": "text/html",
    "date": "Sun, 27 Nov 2022 14:23:19 GMT",
    "last-modified": "Thu, 10 Feb 2022 17:02:30 GMT",
    "nel": "{\"success_fraction\":0,\"report_to\":\"cf-nel\",\"max_age\":604800}",
    "report-to": "{\"endpoints\":[{\"url\":\"https:\\/\\/a.nel.cloudflare.com\\/report\\/v3?s=UJ3dum4M5VCYYeAlA4dp5i5Ua3CWc9i4mHsuNkc%2BxIk0xhjtiT8uGGgUDmsNoaQ4j779VfE%2BY%2Fb%2BrcKjWPbZ%2F9JtjIxf7mosbrYZ1bLfHM4J3pyu99sAOvTtMlY2I5jmWpqwTORBeTt5pRBrc98%3D\"}],\"group\":\"cf-nel\",\"max_age\":604800}",
    "server": "cloudflare",
    "x-amz-id-2": "tx5d5705c22b27442d8d781-00638372d6",
    "x-amz-request-id": "tx5d5705c22b27442d8d781-00638372d6",
    "x-amz-version-id": "1644512550312552"
  },
  "endpoints": [
    {
      "hostname": "territoiresentransitions.fr",
      "ip": "172.67.195.83",
      "geoip": {
        "continent": {
          "code": "NA",
          "geoname_id": 6255149,
          "names": {
            "de": "Nordamerika",
            "en": "North America",
            "es": "Norteamérica",
            "fr": "Amérique du Nord",
            "ja": "北アメリカ",
            "pt-BR": "América do Norte",
            "ru": "Северная Америка",
            "zh-CN": "北美洲"
          }
        },
        "country": {
          "geoname_id": 6252001,
          "iso_code": "US",
          "names": {
            "de": "Vereinigte Staaten",
            "en": "United States",
            "es": "Estados Unidos",
            "fr": "États Unis",
            "ja": "アメリカ",
            "pt-BR": "EUA",
            "ru": "США",
            "zh-CN": "美国"
          }
        },
        "location": {
          "accuracy_radius": 1000,
          "latitude": 37.751,
          "longitude": -97.822,
          "time_zone": "America/Chicago"
        },
        "registered_country": {
          "geoname_id": 6252001,
          "iso_code": "US",
          "names": {
            "de": "Vereinigte Staaten",
            "en": "United States",
            "es": "Estados Unidos",
            "fr": "États Unis",
            "ja": "アメリカ",
            "pt-BR": "EUA",
            "ru": "США",
            "zh-CN": "美国"
          }
        }
      }
    }
  ]
}
