{
  "trackers": [
    {
      "type": "google tag manager",
      "url": "https://www.googletagmanager.com/gtm.js?id=GTM-5S3DCV6",
      "details": {
        "id": "google tag manager",
        "message": "Use hosted Matomo instance"
      }
    },
    {
      "type": "unknown",
      "url": "https://plausible.io/js/plausible.outbound-links.js"
    },
    {
      "type": "unknown",
      "url": "https://static.axept.io/sdk.js"
    },
    {
      "type": "unknown",
      "url": "https://tag.aticdn.net/610648/smarttag.js"
    },
    {
      "type": "xiti",
      "url": "https://logs1409.xiti.com/hit.xiti?s=610648&idclient=424adaf6-0661-4549-bd88-4f302725de20&ts=1649574999664&vtag=5.28.1&ptag=js&r=800x600x24x24&re=800x600&hl=7x16x39&lng=en-US&idp=0716393992512&jv=0&p=/&s2=&ref=",
      "details": {
        "id": "xiti",
        "message": "Use hosted Matomo instance"
      }
    },
    {
      "type": "unknown",
      "url": "https://client.axept.io/606dd246669e09466761ef93.json?r=0"
    },
    {
      "type": "unknown",
      "url": "https://axeptio.imgix.net/2020/09/persos_site_suite_05.png?auto=format&fit=crop&w=96&h=96&dpr=1"
    },
    {
      "type": "unknown",
      "url": "https://axeptio.imgix.net/2021/04/30608171-287f-459c-9ad2-277bc3ff4373.png?auto=format&fit=crop&w=170&h=auto&dpr=1"
    }
  ],
  "cookies": [
    {
      "name": "atuserid",
      "value": "%7B%22name%22%3A%22atuserid%22%2C%22val%22%3A%22424adaf6-0661-4549-bd88-4f302725de20%22%2C%22options%22%3A%7B%22end%22%3A%222023-05-12T07%3A16%3A39.659Z%22%2C%22path%22%3A%22%2F%22%7D%7D",
      "domain": ".jeveuxaider.gouv.fr",
      "path": "/",
      "expires": 1683875799,
      "size": 194,
      "httpOnly": false,
      "secure": false,
      "session": false,
      "sameParty": false,
      "sourceScheme": "Secure",
      "sourcePort": 443
    }
  ],
  "headers": {
    "date": "Sun, 10 Apr 2022 07:16:38 GMT",
    "content-type": "text/html; charset=utf-8",
    "x-request-id": "ae8feddc-5897-40cd-a6c6-7b1f31797def\nae8feddc-5897-40cd-a6c6-7b1f31797def",
    "strict-transport-security": "max-age=31536000",
    "etag": "\"44dd7-Ig62Vya/ecHQo+6VC9oFitKO+4s\"",
    "accept-ranges": "none",
    "vary": "Accept-Encoding",
    "content-encoding": "gzip",
    "expires": "Sun, 10 Apr 2022 07:21:38 GMT",
    "cache-control": "max-age=300\npublic, no-transform",
    "cf-cache-status": "DYNAMIC",
    "expect-ct": "max-age=604800, report-uri=\"https://report-uri.cloudflare.com/cdn-cgi/beacon/expect-ct\"",
    "server": "cloudflare",
    "cf-ray": "6f99b2ba7bd55c23-IAD"
  },
  "endpoints": [
    {
      "hostname": "www.jeveuxaider.gouv.fr",
      "ip": "104.22.77.85",
      "geoip": null
    },
    {
      "hostname": "www.googletagmanager.com",
      "ip": "142.250.73.200",
      "geoip": {
        "continent": {
          "code": "NA",
          "geoname_id": 6255149,
          "names": {
            "de": "Nordamerika",
            "en": "North America",
            "es": "Norteamérica",
            "fr": "Amérique du Nord",
            "ja": "北アメリカ",
            "pt-BR": "América do Norte",
            "ru": "Северная Америка",
            "zh-CN": "北美洲"
          }
        },
        "country": {
          "geoname_id": 6252001,
          "iso_code": "US",
          "names": {
            "de": "Vereinigte Staaten",
            "en": "United States",
            "es": "Estados Unidos",
            "fr": "États Unis",
            "ja": "アメリカ",
            "pt-BR": "EUA",
            "ru": "США",
            "zh-CN": "美国"
          }
        },
        "location": {
          "accuracy_radius": 1000,
          "latitude": 37.751,
          "longitude": -97.822,
          "time_zone": "America/Chicago"
        },
        "registered_country": {
          "geoname_id": 6252001,
          "iso_code": "US",
          "names": {
            "de": "Vereinigte Staaten",
            "en": "United States",
            "es": "Estados Unidos",
            "fr": "États Unis",
            "ja": "アメリカ",
            "pt-BR": "EUA",
            "ru": "США",
            "zh-CN": "美国"
          }
        }
      }
    },
    {
      "hostname": "plausible.io",
      "ip": "37.19.206.70",
      "geoip": {
        "continent": {
          "code": "NA",
          "geoname_id": 6255149,
          "names": {
            "de": "Nordamerika",
            "en": "North America",
            "es": "Norteamérica",
            "fr": "Amérique du Nord",
            "ja": "北アメリカ",
            "pt-BR": "América do Norte",
            "ru": "Северная Америка",
            "zh-CN": "北美洲"
          }
        },
        "country": {
          "geoname_id": 6252001,
          "iso_code": "US",
          "names": {
            "de": "Vereinigte Staaten",
            "en": "United States",
            "es": "Estados Unidos",
            "fr": "États Unis",
            "ja": "アメリカ",
            "pt-BR": "EUA",
            "ru": "США",
            "zh-CN": "美国"
          }
        },
        "location": {
          "accuracy_radius": 1000,
          "latitude": 37.751,
          "longitude": -97.822,
          "time_zone": "America/Chicago"
        },
        "registered_country": {
          "geoname_id": 2635167,
          "iso_code": "GB",
          "names": {
            "de": "Vereinigtes Königreich",
            "en": "United Kingdom",
            "es": "RU",
            "fr": "Royaume Uni",
            "ja": "英国",
            "pt-BR": "Reino Unido",
            "ru": "Британия",
            "zh-CN": "英国"
          }
        }
      }
    },
    {
      "hostname": "static.axept.io",
      "ip": "13.32.207.123",
      "geoip": {
        "continent": {
          "code": "NA",
          "geoname_id": 6255149,
          "names": {
            "de": "Nordamerika",
            "en": "North America",
            "es": "Norteamérica",
            "fr": "Amérique du Nord",
            "ja": "北アメリカ",
            "pt-BR": "América do Norte",
            "ru": "Северная Америка",
            "zh-CN": "北美洲"
          }
        },
        "country": {
          "geoname_id": 6252001,
          "iso_code": "US",
          "names": {
            "de": "Vereinigte Staaten",
            "en": "United States",
            "es": "Estados Unidos",
            "fr": "États Unis",
            "ja": "アメリカ",
            "pt-BR": "EUA",
            "ru": "США",
            "zh-CN": "美国"
          }
        },
        "location": {
          "accuracy_radius": 1000,
          "latitude": 37.751,
          "longitude": -97.822,
          "time_zone": "America/Chicago"
        },
        "registered_country": {
          "geoname_id": 6252001,
          "iso_code": "US",
          "names": {
            "de": "Vereinigte Staaten",
            "en": "United States",
            "es": "Estados Unidos",
            "fr": "États Unis",
            "ja": "アメリカ",
            "pt-BR": "EUA",
            "ru": "США",
            "zh-CN": "美国"
          }
        }
      }
    },
    {
      "hostname": "tag.aticdn.net",
      "ip": "13.32.181.54",
      "geoip": {
        "continent": {
          "code": "NA",
          "geoname_id": 6255149,
          "names": {
            "de": "Nordamerika",
            "en": "North America",
            "es": "Norteamérica",
            "fr": "Amérique du Nord",
            "ja": "北アメリカ",
            "pt-BR": "América do Norte",
            "ru": "Северная Америка",
            "zh-CN": "北美洲"
          }
        },
        "country": {
          "geoname_id": 6252001,
          "iso_code": "US",
          "names": {
            "de": "Vereinigte Staaten",
            "en": "United States",
            "es": "Estados Unidos",
            "fr": "États Unis",
            "ja": "アメリカ",
            "pt-BR": "EUA",
            "ru": "США",
            "zh-CN": "美国"
          }
        },
        "location": {
          "accuracy_radius": 1000,
          "latitude": 37.751,
          "longitude": -97.822,
          "time_zone": "America/Chicago"
        },
        "registered_country": {
          "geoname_id": 6252001,
          "iso_code": "US",
          "names": {
            "de": "Vereinigte Staaten",
            "en": "United States",
            "es": "Estados Unidos",
            "fr": "États Unis",
            "ja": "アメリカ",
            "pt-BR": "EUA",
            "ru": "США",
            "zh-CN": "美国"
          }
        }
      }
    },
    {
      "hostname": "logs1409.xiti.com",
      "ip": "99.86.190.18",
      "geoip": {
        "continent": {
          "code": "NA",
          "geoname_id": 6255149,
          "names": {
            "de": "Nordamerika",
            "en": "North America",
            "es": "Norteamérica",
            "fr": "Amérique du Nord",
            "ja": "北アメリカ",
            "pt-BR": "América do Norte",
            "ru": "Северная Америка",
            "zh-CN": "北美洲"
          }
        },
        "country": {
          "geoname_id": 6252001,
          "iso_code": "US",
          "names": {
            "de": "Vereinigte Staaten",
            "en": "United States",
            "es": "Estados Unidos",
            "fr": "États Unis",
            "ja": "アメリカ",
            "pt-BR": "EUA",
            "ru": "США",
            "zh-CN": "美国"
          }
        },
        "location": {
          "accuracy_radius": 1000,
          "latitude": 37.751,
          "longitude": -97.822,
          "time_zone": "America/Chicago"
        },
        "registered_country": {
          "geoname_id": 6252001,
          "iso_code": "US",
          "names": {
            "de": "Vereinigte Staaten",
            "en": "United States",
            "es": "Estados Unidos",
            "fr": "États Unis",
            "ja": "アメリカ",
            "pt-BR": "EUA",
            "ru": "США",
            "zh-CN": "美国"
          }
        }
      }
    },
    {
      "hostname": "client.axept.io",
      "ip": "13.249.42.7",
      "geoip": {
        "continent": {
          "code": "NA",
          "geoname_id": 6255149,
          "names": {
            "de": "Nordamerika",
            "en": "North America",
            "es": "Norteamérica",
            "fr": "Amérique du Nord",
            "ja": "北アメリカ",
            "pt-BR": "América do Norte",
            "ru": "Северная Америка",
            "zh-CN": "北美洲"
          }
        },
        "country": {
          "geoname_id": 6252001,
          "iso_code": "US",
          "names": {
            "de": "Vereinigte Staaten",
            "en": "United States",
            "es": "Estados Unidos",
            "fr": "États Unis",
            "ja": "アメリカ",
            "pt-BR": "EUA",
            "ru": "США",
            "zh-CN": "美国"
          }
        },
        "location": {
          "accuracy_radius": 1000,
          "latitude": 37.751,
          "longitude": -97.822,
          "time_zone": "America/Chicago"
        },
        "registered_country": {
          "geoname_id": 6252001,
          "iso_code": "US",
          "names": {
            "de": "Vereinigte Staaten",
            "en": "United States",
            "es": "Estados Unidos",
            "fr": "États Unis",
            "ja": "アメリカ",
            "pt-BR": "EUA",
            "ru": "США",
            "zh-CN": "美国"
          }
        }
      }
    },
    {
      "hostname": "axeptio.imgix.net",
      "ip": "146.75.30.208",
      "geoip": {
        "city": {
          "geoname_id": 4744870,
          "names": {
            "en": "Ashburn",
            "ru": "Ашберн"
          }
        },
        "continent": {
          "code": "NA",
          "geoname_id": 6255149,
          "names": {
            "de": "Nordamerika",
            "en": "North America",
            "es": "Norteamérica",
            "fr": "Amérique du Nord",
            "ja": "北アメリカ",
            "pt-BR": "América do Norte",
            "ru": "Северная Америка",
            "zh-CN": "北美洲"
          }
        },
        "country": {
          "geoname_id": 6252001,
          "iso_code": "US",
          "names": {
            "de": "Vereinigte Staaten",
            "en": "United States",
            "es": "Estados Unidos",
            "fr": "États Unis",
            "ja": "アメリカ",
            "pt-BR": "EUA",
            "ru": "США",
            "zh-CN": "美国"
          }
        },
        "location": {
          "accuracy_radius": 1000,
          "latitude": 39.018,
          "longitude": -77.539,
          "metro_code": 511,
          "time_zone": "America/New_York"
        },
        "postal": {
          "code": "20147"
        },
        "registered_country": {
          "geoname_id": 6252001,
          "iso_code": "US",
          "names": {
            "de": "Vereinigte Staaten",
            "en": "United States",
            "es": "Estados Unidos",
            "fr": "États Unis",
            "ja": "アメリカ",
            "pt-BR": "EUA",
            "ru": "США",
            "zh-CN": "美国"
          }
        },
        "subdivisions": [
          {
            "geoname_id": 6254928,
            "iso_code": "VA",
            "names": {
              "en": "Virginia",
              "fr": "Virginie",
              "ja": "バージニア州",
              "pt-BR": "Virgínia",
              "ru": "Вирджиния",
              "zh-CN": "弗吉尼亚州"
            }
          }
        ]
      }
    }
  ]
}
