{
  "trackers": [],
  "cookies": [
    {
      "name": "connect.sid",
      "value": "s%3A91gInhCgi4Rb-aKoSW35ck0_fYeSYrje.fsQasSjxrVjtSfsTjdz36rSSzOWGWScuA1KF%2FdzucTI",
      "domain": "pad.incubateur.net",
      "path": "/",
      "expires": 1631165359.79028,
      "size": 93,
      "httpOnly": true,
      "secure": true,
      "session": false,
      "sameSite": "Lax",
      "sameParty": false,
      "sourceScheme": "Secure",
      "sourcePort": 443
    }
  ],
  "headers": {
    "server": "openresty",
    "date": "Thu, 26 Aug 2021 05:29:19 GMT",
    "content-type": "text/html; charset=utf-8",
    "x-request-id": "8aaf455e-cb7e-4189-ad64-539282adfd47",
    "strict-transport-security": "max-age=31536000\nmax-age=31536000; includeSubDomains; preload",
    "x-powered-by": "Express",
    "referrer-policy": "same-origin",
    "content-security-policy": "default-src 'none';base-uri 'self';connect-src 'self';font-src 'self';manifest-src 'self';frame-src 'self' https://player.vimeo.com https://www.slideshare.net/slideshow/embed_code/key/ https://www.youtube.com *;img-src *;script-src https://pad.incubateur.net/build/ https://pad.incubateur.net/js/ https://pad.incubateur.net/config https://gist.github.com/ https://vimeo.com/api/oembed.json https://www.slideshare.net/api/oembed/2 'unsafe-inline' 'nonce-9838c500-b692-406a-b638-5e5c93c8ed40' 'sha256-81acLZNZISnyGYZrSuoYhpzwDTTxi7vC1YM4uNxqWaM=';style-src https://pad.incubateur.net/build/ https://pad.incubateur.net/css/ 'unsafe-inline' https://github.githubassets.com;object-src * *;form-action 'self';media-src *;upgrade-insecure-requests",
    "hedgedoc-version": "1.8.2",
    "etag": "W/\"3a7e-uAP1WecOIivF100oF9HC7++QfMc\"",
    "set-cookie": "connect.sid=s%3A91gInhCgi4Rb-aKoSW35ck0_fYeSYrje.fsQasSjxrVjtSfsTjdz36rSSzOWGWScuA1KF%2FdzucTI; Path=/; Expires=Thu, 09 Sep 2021 05:29:19 GMT; HttpOnly; Secure; SameSite=Lax",
    "vary": "Accept-Encoding",
    "content-encoding": "gzip"
  },
  "endpoints": [
    {
      "hostname": "pad.incubateur.net",
      "ip": "5.104.101.30",
      "geoip": {
        "continent": {
          "code": "EU",
          "geoname_id": 6255148,
          "names": {
            "de": "Europa",
            "en": "Europe",
            "es": "Europa",
            "fr": "Europe",
            "ja": "ヨーロッパ",
            "pt-BR": "Europa",
            "ru": "Европа",
            "zh-CN": "欧洲"
          }
        },
        "country": {
          "geoname_id": 3017382,
          "is_in_european_union": true,
          "iso_code": "FR",
          "names": {
            "de": "Frankreich",
            "en": "France",
            "es": "Francia",
            "fr": "France",
            "ja": "フランス共和国",
            "pt-BR": "França",
            "ru": "Франция",
            "zh-CN": "法国"
          }
        },
        "location": {
          "accuracy_radius": 500,
          "latitude": 48.8582,
          "longitude": 2.3387,
          "time_zone": "Europe/Paris"
        },
        "registered_country": {
          "geoname_id": 3017382,
          "is_in_european_union": true,
          "iso_code": "FR",
          "names": {
            "de": "Frankreich",
            "en": "France",
            "es": "Francia",
            "fr": "France",
            "ja": "フランス共和国",
            "pt-BR": "França",
            "ru": "Франция",
            "zh-CN": "法国"
          }
        }
      }
    }
  ]
}
